snx/__init__.py
snx/analyzer.py
snx/ast.py
snx/cfg.py
snx/checker.py
snx/cli.py
snx/compiler.py
snx/constants.py
snx/dataflow.py
snx/diagnostics.py
snx/encoding.py
snx/parser.py
snx/runner.py
snx/simulator.py
snx/tokenizer.py
snx/trace.py
snx/word.py
snx_simulator-0.2.4.dist-info/METADATA
snx_simulator-0.2.4.dist-info/WHEEL
snx_simulator-0.2.4.dist-info/entry_points.txt
snx_simulator-0.2.4.dist-info/licenses/LICENSE
snx_simulator-0.2.4.dist-info/RECORD
