Metadata-Version: 2.4
Name: snx-simulator
Version: 0.2.4
Summary: sn/x architecture assembly code simulator
License: Copyright (c) 2025 Jun Koo (snowykr)
License-File: LICENSE
Classifier: License :: OSI Approved :: MIT License
Requires-Python: >=3.11
